{
  "bbox": [
    0,
    0,
    25600,
    8400
  ],
  "globalRoutes": [],
  "globalRouteGrid": [],
  "terminals": [
    {
      "layer": "M1",
      "netName": "DA",
      "rect": [
        3840,
        1320,
        4160,
        7920
      ]
    },
    {
      "layer": "M1",
      "netName": "S",
      "rect": [
        3040,
        1320,
        3360,
        7920
      ]
    },
    {
      "layer": "M1",
      "netName": "SA",
      "rect": [
        4640,
        1320,
        4960,
        7920
      ]
    },
    {
      "layer": "M1",
      "netName": "DA",
      "rect": [
        10240,
        1320,
        10560,
        7920
      ]
    },
    {
      "layer": "M1",
      "netName": "S",
      "rect": [
        9440,
        1320,
        9760,
        7920
      ]
    },
    {
      "layer": "M1",
      "netName": "SB",
      "rect": [
        11040,
        1320,
        11360,
        7920
      ]
    },
    {
      "layer": "M1",
      "netName": "DA",
      "rect": [
        16640,
        1320,
        16960,
        7920
      ]
    },
    {
      "layer": "M1",
      "netName": "S",
      "rect": [
        15840,
        1320,
        16160,
        7920
      ]
    },
    {
      "layer": "M1",
      "netName": "SA",
      "rect": [
        17440,
        1320,
        17760,
        7920
      ]
    },
    {
      "layer": "M1",
      "netName": "DA",
      "rect": [
        23040,
        1320,
        23360,
        7920
      ]
    },
    {
      "layer": "M1",
      "netName": "S",
      "rect": [
        22240,
        1320,
        22560,
        7920
      ]
    },
    {
      "layer": "M1",
      "netName": "SB",
      "rect": [
        23840,
        1320,
        24160,
        7920
      ]
    },
    {
      "layer": "M1",
      "netName": "DA",
      "rect": [
        29440,
        1320,
        29760,
        7920
      ]
    },
    {
      "layer": "M1",
      "netName": "S",
      "rect": [
        28640,
        1320,
        28960,
        7920
      ]
    },
    {
      "layer": "M1",
      "netName": "SA",
      "rect": [
        30240,
        1320,
        30560,
        7920
      ]
    },
    {
      "layer": "M1",
      "netName": "DA",
      "rect": [
        35840,
        1320,
        36160,
        7920
      ]
    },
    {
      "layer": "M1",
      "netName": "S",
      "rect": [
        35040,
        1320,
        35360,
        7920
      ]
    },
    {
      "layer": "M1",
      "netName": "SB",
      "rect": [
        36640,
        1320,
        36960,
        7920
      ]
    },
    {
      "layer": "M2",
      "netName": "S",
      "rect": [
        2840,
        1520,
        35560,
        1840
      ]
    },
    {
      "layer": "M2",
      "netName": "S",
      "rect": [
        2840,
        4880,
        35560,
        5200
      ]
    },
    {
      "layer": "M2",
      "netName": "SA",
      "rect": [
        4440,
        2360,
        30760,
        2680
      ]
    },
    {
      "layer": "M2",
      "netName": "SA",
      "rect": [
        4440,
        5720,
        30760,
        6040
      ]
    },
    {
      "layer": "M2",
      "netName": "SB",
      "rect": [
        10840,
        3200,
        37160,
        3520
      ]
    },
    {
      "layer": "M2",
      "netName": "SB",
      "rect": [
        10840,
        6560,
        37160,
        6880
      ]
    },
    {
      "layer": "M2",
      "netName": "DA",
      "rect": [
        3640,
        4040,
        36360,
        4360
      ]
    },
    {
      "layer": "M2",
      "netName": "DA",
      "rect": [
        3640,
        7400,
        36360,
        7720
      ]
    },
    {
      "layer": "V1",
      "netName": "S",
      "rect": [
        28640,
        1520,
        28960,
        1840
      ]
    },
    {
      "layer": "V1",
      "netName": "S",
      "rect": [
        28640,
        4880,
        28960,
        5200
      ]
    },
    {
      "layer": "V1",
      "netName": "S",
      "rect": [
        3040,
        1520,
        3360,
        1840
      ]
    },
    {
      "layer": "V1",
      "netName": "S",
      "rect": [
        3040,
        4880,
        3360,
        5200
      ]
    },
    {
      "layer": "V1",
      "netName": "S",
      "rect": [
        9440,
        1520,
        9760,
        1840
      ]
    },
    {
      "layer": "V1",
      "netName": "S",
      "rect": [
        9440,
        4880,
        9760,
        5200
      ]
    },
    {
      "layer": "V1",
      "netName": "S",
      "rect": [
        35040,
        1520,
        35360,
        1840
      ]
    },
    {
      "layer": "V1",
      "netName": "S",
      "rect": [
        35040,
        4880,
        35360,
        5200
      ]
    },
    {
      "layer": "V1",
      "netName": "S",
      "rect": [
        15840,
        1520,
        16160,
        1840
      ]
    },
    {
      "layer": "V1",
      "netName": "S",
      "rect": [
        15840,
        4880,
        16160,
        5200
      ]
    },
    {
      "layer": "V1",
      "netName": "S",
      "rect": [
        22240,
        1520,
        22560,
        1840
      ]
    },
    {
      "layer": "V1",
      "netName": "S",
      "rect": [
        22240,
        4880,
        22560,
        5200
      ]
    },
    {
      "layer": "V1",
      "netName": "SA",
      "rect": [
        17440,
        2360,
        17760,
        2680
      ]
    },
    {
      "layer": "V1",
      "netName": "SA",
      "rect": [
        17440,
        5720,
        17760,
        6040
      ]
    },
    {
      "layer": "V1",
      "netName": "SA",
      "rect": [
        30240,
        2360,
        30560,
        2680
      ]
    },
    {
      "layer": "V1",
      "netName": "SA",
      "rect": [
        30240,
        5720,
        30560,
        6040
      ]
    },
    {
      "layer": "V1",
      "netName": "SA",
      "rect": [
        4640,
        2360,
        4960,
        2680
      ]
    },
    {
      "layer": "V1",
      "netName": "SA",
      "rect": [
        4640,
        5720,
        4960,
        6040
      ]
    },
    {
      "layer": "V1",
      "netName": "SB",
      "rect": [
        23840,
        3200,
        24160,
        3520
      ]
    },
    {
      "layer": "V1",
      "netName": "SB",
      "rect": [
        23840,
        6560,
        24160,
        6880
      ]
    },
    {
      "layer": "V1",
      "netName": "SB",
      "rect": [
        36640,
        3200,
        36960,
        3520
      ]
    },
    {
      "layer": "V1",
      "netName": "SB",
      "rect": [
        36640,
        6560,
        36960,
        6880
      ]
    },
    {
      "layer": "V1",
      "netName": "SB",
      "rect": [
        11040,
        3200,
        11360,
        3520
      ]
    },
    {
      "layer": "V1",
      "netName": "SB",
      "rect": [
        11040,
        6560,
        11360,
        6880
      ]
    },
    {
      "layer": "V1",
      "netName": "DA",
      "rect": [
        3840,
        4040,
        4160,
        4360
      ]
    },
    {
      "layer": "V1",
      "netName": "DA",
      "rect": [
        3840,
        7400,
        4160,
        7720
      ]
    },
    {
      "layer": "V1",
      "netName": "DA",
      "rect": [
        29440,
        4040,
        29760,
        4360
      ]
    },
    {
      "layer": "V1",
      "netName": "DA",
      "rect": [
        29440,
        7400,
        29760,
        7720
      ]
    },
    {
      "layer": "V1",
      "netName": "DA",
      "rect": [
        10240,
        4040,
        10560,
        4360
      ]
    },
    {
      "layer": "V1",
      "netName": "DA",
      "rect": [
        10240,
        7400,
        10560,
        7720
      ]
    },
    {
      "layer": "V1",
      "netName": "DA",
      "rect": [
        35840,
        4040,
        36160,
        4360
      ]
    },
    {
      "layer": "V1",
      "netName": "DA",
      "rect": [
        35840,
        7400,
        36160,
        7720
      ]
    },
    {
      "layer": "V1",
      "netName": "DA",
      "rect": [
        16640,
        4040,
        16960,
        4360
      ]
    },
    {
      "layer": "V1",
      "netName": "DA",
      "rect": [
        16640,
        7400,
        16960,
        7720
      ]
    },
    {
      "layer": "V1",
      "netName": "DA",
      "rect": [
        23040,
        4040,
        23360,
        4360
      ]
    },
    {
      "layer": "V1",
      "netName": "DA",
      "rect": [
        23040,
        7400,
        23360,
        7720
      ]
    },
    {
      "layer": "M3",
      "netName": "S",
      "rect": [
        17400,
        1320,
        17800,
        5400
      ]
    },
    {
      "layer": "M3",
      "netName": "S",
      "rect": [
        20600,
        1320,
        21000,
        5400
      ]
    },
    {
      "layer": "M3",
      "netName": "SA",
      "rect": [
        18200,
        2160,
        18600,
        6240
      ]
    },
    {
      "layer": "M3",
      "netName": "SA",
      "rect": [
        21400,
        2160,
        21800,
        6240
      ]
    },
    {
      "layer": "M3",
      "netName": "SB",
      "rect": [
        19000,
        3000,
        19400,
        7080
      ]
    },
    {
      "layer": "M3",
      "netName": "SB",
      "rect": [
        22200,
        3000,
        22600,
        7080
      ]
    },
    {
      "layer": "M3",
      "netName": "DA",
      "rect": [
        19800,
        3840,
        20200,
        7920
      ]
    },
    {
      "layer": "M3",
      "netName": "DA",
      "rect": [
        23000,
        3840,
        23400,
        7920
      ]
    },
    {
      "layer": "V2",
      "netName": "S",
      "rect": [
        17440,
        1520,
        17760,
        1840
      ]
    },
    {
      "layer": "V2",
      "netName": "S",
      "rect": [
        17440,
        4880,
        17760,
        5200
      ]
    },
    {
      "layer": "V2",
      "netName": "S",
      "rect": [
        20640,
        1520,
        20960,
        1840
      ]
    },
    {
      "layer": "V2",
      "netName": "S",
      "rect": [
        20640,
        4880,
        20960,
        5200
      ]
    },
    {
      "layer": "V2",
      "netName": "SA",
      "rect": [
        18240,
        2360,
        18560,
        2680
      ]
    },
    {
      "layer": "V2",
      "netName": "SA",
      "rect": [
        18240,
        5720,
        18560,
        6040
      ]
    },
    {
      "layer": "V2",
      "netName": "SA",
      "rect": [
        21440,
        2360,
        21760,
        2680
      ]
    },
    {
      "layer": "V2",
      "netName": "SA",
      "rect": [
        21440,
        5720,
        21760,
        6040
      ]
    },
    {
      "layer": "V2",
      "netName": "SB",
      "rect": [
        19040,
        3200,
        19360,
        3520
      ]
    },
    {
      "layer": "V2",
      "netName": "SB",
      "rect": [
        19040,
        6560,
        19360,
        6880
      ]
    },
    {
      "layer": "V2",
      "netName": "SB",
      "rect": [
        22240,
        3200,
        22560,
        3520
      ]
    },
    {
      "layer": "V2",
      "netName": "SB",
      "rect": [
        22240,
        6560,
        22560,
        6880
      ]
    },
    {
      "layer": "V2",
      "netName": "DA",
      "rect": [
        19840,
        4040,
        20160,
        4360
      ]
    },
    {
      "layer": "V2",
      "netName": "DA",
      "rect": [
        19840,
        7400,
        20160,
        7720
      ]
    },
    {
      "layer": "V2",
      "netName": "DA",
      "rect": [
        23040,
        4040,
        23360,
        4360
      ]
    },
    {
      "layer": "V2",
      "netName": "DA",
      "rect": [
        23040,
        7400,
        23360,
        7720
      ]
    },
    {
      "layer": "M1",
      "netName": "GA",
      "rect": [
        10240,
        10560,
        10560,
        17160
      ]
    },
    {
      "layer": "M1",
      "netName": "SA",
      "rect": [
        9440,
        10560,
        9760,
        17160
      ]
    },
    {
      "layer": "M1",
      "netName": "DA",
      "rect": [
        11040,
        10560,
        11360,
        17160
      ]
    },
    {
      "layer": "M1",
      "netName": "GA",
      "rect": [
        16640,
        10560,
        16960,
        17160
      ]
    },
    {
      "layer": "M1",
      "netName": "SB",
      "rect": [
        15840,
        10560,
        16160,
        17160
      ]
    },
    {
      "layer": "M1",
      "netName": "DB",
      "rect": [
        17440,
        10560,
        17760,
        17160
      ]
    },
    {
      "layer": "M1",
      "netName": "GA",
      "rect": [
        23040,
        10560,
        23360,
        17160
      ]
    },
    {
      "layer": "M1",
      "netName": "SB",
      "rect": [
        23840,
        10560,
        24160,
        17160
      ]
    },
    {
      "layer": "M1",
      "netName": "DB",
      "rect": [
        22240,
        10560,
        22560,
        17160
      ]
    },
    {
      "layer": "M1",
      "netName": "GA",
      "rect": [
        29440,
        10560,
        29760,
        17160
      ]
    },
    {
      "layer": "M1",
      "netName": "SA",
      "rect": [
        30240,
        10560,
        30560,
        17160
      ]
    },
    {
      "layer": "M1",
      "netName": "DA",
      "rect": [
        28640,
        10560,
        28960,
        17160
      ]
    },
    {
      "layer": "M2",
      "netName": "SA",
      "rect": [
        9240,
        10760,
        30760,
        11080
      ]
    },
    {
      "layer": "M2",
      "netName": "DA",
      "rect": [
        10840,
        11600,
        29160,
        11920
      ]
    },
    {
      "layer": "M2",
      "netName": "SB",
      "rect": [
        15640,
        12440,
        24360,
        12760
      ]
    },
    {
      "layer": "M2",
      "netName": "DB",
      "rect": [
        17240,
        13280,
        22760,
        13600
      ]
    },
    {
      "layer": "M2",
      "netName": "GA",
      "rect": [
        10040,
        14120,
        29960,
        14440
      ]
    },
    {
      "layer": "V1",
      "netName": "SA",
      "rect": [
        9440,
        10760,
        9760,
        11080
      ]
    },
    {
      "layer": "V1",
      "netName": "SA",
      "rect": [
        30240,
        10760,
        30560,
        11080
      ]
    },
    {
      "layer": "V1",
      "netName": "DA",
      "rect": [
        28640,
        11600,
        28960,
        11920
      ]
    },
    {
      "layer": "V1",
      "netName": "DA",
      "rect": [
        11040,
        11600,
        11360,
        11920
      ]
    },
    {
      "layer": "V1",
      "netName": "SB",
      "rect": [
        15840,
        12440,
        16160,
        12760
      ]
    },
    {
      "layer": "V1",
      "netName": "SB",
      "rect": [
        23840,
        12440,
        24160,
        12760
      ]
    },
    {
      "layer": "V1",
      "netName": "DB",
      "rect": [
        22240,
        13280,
        22560,
        13600
      ]
    },
    {
      "layer": "V1",
      "netName": "DB",
      "rect": [
        17440,
        13280,
        17760,
        13600
      ]
    },
    {
      "layer": "V1",
      "netName": "GA",
      "rect": [
        16640,
        14120,
        16960,
        14440
      ]
    },
    {
      "layer": "V1",
      "netName": "GA",
      "rect": [
        23040,
        14120,
        23360,
        14440
      ]
    },
    {
      "layer": "V1",
      "netName": "GA",
      "rect": [
        10240,
        14120,
        10560,
        14440
      ]
    },
    {
      "layer": "V1",
      "netName": "GA",
      "rect": [
        29440,
        14120,
        29760,
        14440
      ]
    },
    {
      "netName": "SA",
      "layer": "M3",
      "rect": [
        18200,
        2160,
        18600,
        6240
      ]
    },
    {
      "netName": "SA",
      "layer": "M3",
      "rect": [
        21400,
        2160,
        21800,
        6240
      ]
    },
    {
      "netName": "SA",
      "layer": "M2",
      "rect": [
        9240,
        10760,
        30760,
        11080
      ]
    },
    {
      "netName": "SA",
      "layer": "M3",
      "rect": [
        18200,
        5880,
        18600,
        10920
      ]
    },
    {
      "netName": "SA",
      "layer": "M2",
      "rect": [
        18240,
        10760,
        18560,
        11080
      ]
    },
    {
      "netName": "SA",
      "layer": "M3",
      "rect": [
        18200,
        10560,
        18600,
        11280
      ]
    },
    {
      "netName": "SA",
      "layer": "M2",
      "rect": [
        18040,
        10760,
        18760,
        11080
      ]
    },
    {
      "netName": "SA",
      "layer": "V2",
      "rect": [
        18240,
        10760,
        18560,
        11080
      ]
    },
    {
      "netName": "DA",
      "layer": "M3",
      "rect": [
        19800,
        3840,
        20200,
        7920
      ]
    },
    {
      "netName": "DA",
      "layer": "M3",
      "rect": [
        23000,
        3840,
        23400,
        7920
      ]
    },
    {
      "netName": "DA",
      "layer": "M2",
      "rect": [
        10840,
        11600,
        29160,
        11920
      ]
    },
    {
      "netName": "DA",
      "layer": "M3",
      "rect": [
        19800,
        6720,
        20200,
        11760
      ]
    },
    {
      "netName": "DA",
      "layer": "M2",
      "rect": [
        19840,
        11600,
        20160,
        11920
      ]
    },
    {
      "netName": "DA",
      "layer": "M3",
      "rect": [
        19800,
        11400,
        20200,
        12120
      ]
    },
    {
      "netName": "DA",
      "layer": "M2",
      "rect": [
        19640,
        11600,
        20360,
        11920
      ]
    },
    {
      "netName": "DA",
      "layer": "V2",
      "rect": [
        19840,
        11600,
        20160,
        11920
      ]
    },
    {
      "netName": "SB",
      "layer": "M3",
      "rect": [
        19000,
        3000,
        19400,
        7080
      ]
    },
    {
      "netName": "SB",
      "layer": "M3",
      "rect": [
        22200,
        3000,
        22600,
        7080
      ]
    },
    {
      "netName": "SB",
      "layer": "M2",
      "rect": [
        15640,
        12440,
        24360,
        12760
      ]
    },
    {
      "netName": "SB",
      "layer": "M3",
      "rect": [
        22200,
        4840,
        22600,
        5240
      ]
    },
    {
      "netName": "SB",
      "layer": "M4",
      "rect": [
        22400,
        4840,
        24000,
        5240
      ]
    },
    {
      "netName": "SB",
      "layer": "M3",
      "rect": [
        23800,
        5040,
        24200,
        12600
      ]
    },
    {
      "netName": "SB",
      "layer": "M2",
      "rect": [
        23840,
        12440,
        24160,
        12760
      ]
    },
    {
      "netName": "SB",
      "layer": "M3",
      "rect": [
        23800,
        12240,
        24200,
        12960
      ]
    },
    {
      "netName": "SB",
      "layer": "M2",
      "rect": [
        23640,
        12440,
        24360,
        12760
      ]
    },
    {
      "netName": "SB",
      "layer": "V2",
      "rect": [
        23840,
        12440,
        24160,
        12760
      ]
    },
    {
      "netName": "SB",
      "layer": "M4",
      "rect": [
        22000,
        4840,
        22800,
        5240
      ]
    },
    {
      "netName": "SB",
      "layer": "M3",
      "rect": [
        22200,
        4640,
        22600,
        5440
      ]
    },
    {
      "netName": "SB",
      "layer": "V3",
      "rect": [
        22200,
        4840,
        22600,
        5240
      ]
    },
    {
      "netName": "SB",
      "layer": "M4",
      "rect": [
        23600,
        4840,
        24400,
        5240
      ]
    },
    {
      "netName": "SB",
      "layer": "M3",
      "rect": [
        23800,
        4640,
        24200,
        5440
      ]
    },
    {
      "netName": "SB",
      "layer": "V3",
      "rect": [
        23800,
        4840,
        24200,
        5240
      ]
    },
    {
      "netName": "S",
      "layer": "M3",
      "rect": [
        17400,
        1320,
        17800,
        5400
      ]
    },
    {
      "netName": "S",
      "layer": "M3",
      "rect": [
        20600,
        1320,
        21000,
        5400
      ]
    },
    {
      "netName": "GA",
      "layer": "M2",
      "rect": [
        10040,
        14120,
        29960,
        14440
      ]
    },
    {
      "netName": "DB",
      "layer": "M2",
      "rect": [
        17240,
        13280,
        22760,
        13600
      ]
    }
  ]
}